drag/utils.py
drag/base/base.py
drag/chroma_db/chroma.py
drag/commands/drag_clean.py
drag/groq/groq_chat.py
drag/openai/openai_chat.py
drag/qdrant_db/qdrant.py
drag_ai-0.0.1.dist-info/LICENSE
drag_ai-0.0.1.dist-info/METADATA
drag_ai-0.0.1.dist-info/WHEEL
drag_ai-0.0.1.dist-info/top_level.txt
drag_ai-0.0.1.dist-info/RECORD
