Metadata-Version: 2.1
Name: drag-ai
Version: 0.0.1
Summary: A notebook copilot for data analysis
Author-email: Gabriele Caletti <calettigabriele@gmail.com>
Project-URL: Homepage, https://github.com/CalettiGabriele/DRAG
Keywords: llm,notebook,analysis
License-File: LICENSE
Requires-Dist: pandas
Requires-Dist: numpy
Requires-Dist: matplotlib
Requires-Dist: python-pptx
Requires-Dist: groq
Requires-Dist: openai
Requires-Dist: chromadb
Requires-Dist: nbformat
Requires-Dist: nbconvert
